<?xml version="1.0" encoding="UTF-8" standalone="yes"?>

<item>
<title>Mana </title>        
<urlsolve>https://www.youtube.com/watch?v=5cSwBC_Z8e8</urlsolve>
<thumbnail>http://getin.com.mx/wp-content/uploads/2015/01/mana.png</thumbnail>
<fanart>https://i.ytimg.com/vi/19BEplfdAb0/maxresdefault.jpg</fanart>
</item>

<item>
<title>David Bisbal - premonicion live-concierto   </title>        
<urlsolve>https://www.youtube.com/watch?v=HEigVFltQ90</urlsolve>
<thumbnail>http://images5.fanpop.com/image/photos/30500000/David-Bisbal-david-bisbal-passion-gitana-30571379-1024-768.jpg</thumbnail>
<fanart>http://static1.elnortedecastilla.es/www/multimedia/201803/22/media/cortadas/bisbal-kEKB-U501368135496HfC-624x385@El%20Norte.jpg</fanart>
</item>

<item>
<title>Cristian Castro Zócalo de México 2003 (Concierto Completo)   </title>        
<urlsolve>https://www.youtube.com/watch?v=TMI6XnDo7q4</urlsolve>
<thumbnail>http://cache.vevo.com/Content/VevoImages/video/a1edac6fea1ed2cb1472a832941899e02015178135640532.jpg</thumbnail>
<fanart>https://upload.wikimedia.org/wikipedia/commons/thumb/7/72/Cristian_castro_vivo_2.jpg/1200px-Cristian_castro_vivo_2.jpg</fanart>
</item>

<item>
<title>Shakira | Viña del Mar 1997   </title>        
<urlsolve>https://www.youtube.com/watch?v=Zu29vv4_Ahk</urlsolve>
<thumbnail>http://img2.timeinc.net/people/i/2007/startracks/070409/shakira.jpg</thumbnail>
<fanart>http://1.bp.blogspot.com/-noBC5XMs5Dk/TrKv7rfLGmI/AAAAAAAACmM/kXJbXE-0tBM/s1600/shakira-22.jpg</fanart>
</item>

<item>
<title>La Quinta Estación Básico 40 Completo   </title>        
<urlsolve>https://www.youtube.com/watch?v=I2fz9sVg1TA</urlsolve>
<thumbnail>https://lh6.googleusercontent.com/-BeUoGl1siXE/UQijCTbYlTI/AAAAAAADsrA/vYaGZXyzdOk/s1600/la-quinta-estacion-5-003.png</thumbnail>
<fanart>https://aprenderespanolenmadrid.files.wordpress.com/2015/10/la-quinta-estacion-02.jpg</fanart>
</item>

<item>
<title>La Oreja De VanGogh GIRA 2003   </title>        
<urlsolve>https://www.youtube.com/watch?v=ohhzJTqxo0Q</urlsolve>
<thumbnail>http://www.vuelvelaoreja.com/images/logo.png</thumbnail>
<fanart>https://i.ytimg.com/vi/bqJAFnruMHc/maxresdefault.jpg</fanart>
</item>

<item>
<title>La Oreja de Van Gogh en el Festival de Peñas Villa María 2014    </title>        
<urlsolve>https://www.youtube.com/watch?v=0guRPSc5DU8</urlsolve>
<thumbnail>https://fanart.tv/fanart/music/a7c38944-b3fa-4a3d-a4bd-d3b3b06f0cbf/hdmusiclogo/oreja-de-van-gogh-la-569014d7a3ca0.png</thumbnail>
<fanart>https://fanart.tv/fanart/music/a7c38944-b3fa-4a3d-a4bd-d3b3b06f0cbf/artistbackground/oreja-de-van-gogh-la-4fbaa1b7999c5.jpg</fanart>
</item>

<item>
<title>Concierto completo de RBD en Mexico    </title>        
<urlsolve>https://www.youtube.com/watch?v=jWoo7x8ZDoQ</urlsolve>
<thumbnail>https://art-s.nflximg.net/acc11/c797da7f55ad5bb650b37779bc7525cdfb9acc11.png</thumbnail>
<fanart>https://i.ytimg.com/vi/Dz6J4Z792O0/maxresdefault.jpg</fanart>
</item>

<item>
<title>Los Rabanes live from The House of Music Guaynabo Puerto Rico   </title>        
<urlsolve>https://www.youtube.com/watch?v=dJVTrMxC_h0</urlsolve>
<thumbnail>http://www.budfestpanama.com/images/2017/06/12/rabanes.png</thumbnail>
<fanart>http://www.sonidosaustin.com/wp-content/uploads/2016/06/rabanes-2.jpg</fanart>
</item>

<item>
<title>¡Revive el romántico show de Jesse & Joy! | Festival de Talca 2017    </title>        
<urlsolve>https://www.youtube.com/watch?v=aa9keH6ROoY&t=1493s</urlsolve>
<thumbnail>http://rossanamusica.com/portal/wp-content/uploads/2012/12/Jesse-Joy-1-12-06-12.png</thumbnail>
<fanart>https://media.livenation.com/artists/81410/81410-show-66374.jpg?1374690681</fanart>
</item>

<item>
<title>Ha*Ash Concierto Completo en Lima - Perú 2016   </title>        
<urlsolve>https://www.youtube.com/watch?v=KqnS_PgYMuA&t=190s</urlsolve>
<thumbnail>http://los40mx00.epimg.net/especiales/lanzamiento40/ha-ash/img/logo.png</thumbnail>
<fanart>http://www.billboard.com/files/media/Ha-ash-tour-2016-billboard-650.jpg</fanart>
</item>

<item>
<title>Gloria Trevi & Alejandra Guzmán: Versus Tour (En Vivo Desde Arena Ciudad de Mexico)   </title>        
<urlsolve>https://www.youtube.com/watch?v=_ntgciqvhtE</urlsolve>
<thumbnail>http://gritaradio.com/files/2017/01/GLORIA-TREVI-Y-ALEJANDRA-GUZMAN.jpg</thumbnail>
<fanart>https://i.ytimg.com/vi/K1T2Q0kEl9w/maxresdefault.jpg</fanart>
</item>

<item>
<title>GLORIA TREVI en el Auditorio Nacional, completo    </title>        
<urlsolve>https://www.youtube.com/watch?v=gBhVn4Zci2Y</urlsolve>
<thumbnail>http://www.latrevi.com.mx/pub/img/logo.png</thumbnail>
<fanart>http://images.latintimes.com/sites/latintimes.com/files/styles/large/public/2016/06/30/gloria-trevi.jpg</fanart>
</item>

<item>
<title>Paulina Rubio en Viña 2005 (Show completo)   </title>        
<urlsolve>https://www.youtube.com/watch?v=-r_IJumpJ9Y</urlsolve>
<thumbnail>http://www.hawtcelebs.com/wp-content/uploads/2017/07/best-from-the-past-paulina-rubio-for-gran-city-pop-2009_1.jpg</thumbnail>
<fanart>http://media1.santabanta.com/full1/Global%20Celebrities(F)/Paulina%20Rubio/paulina-rubio-9a.jpg</fanart>
</item>

<item>
<title>Laura Pausini en Viña 2014 Completo HD VIÑA 2014   </title>        
<urlsolve>https://www.youtube.com/watch?v=9_4I1p71gKk</urlsolve>
<thumbnail>http://www.rai.it/dl/img/2016/01/1453369354899pausini.png</thumbnail>
<fanart>http://www.fmdos.cl/wp-content/uploads/2014/02/laura-pausini-1027.jpg</fanart>
</item>

<item>
<title>alex campos te puedo sentir completo   </title>        
<urlsolve>https://www.youtube.com/watch?v=Q33m6HiZHC0</urlsolve>
<thumbnail>http://www.fuentedevida.com/assets/images/images/audiocd/ac.envivo.front.jpg</thumbnail>
<fanart>https://www.clickgratis.com.br/fotos-imagens/alex-campos/aHR0cDovL2Nkbi5zb25pY29tdXNpY2EuY29tL2FydGlzdHMvYS9hbGV4LWNhbXBvcy9hbGV4LWNhbXBvcy02LmpwZw==.jpg</fanart>
</item>

<item>
<title>INGRID ROSARIO EN CONCIERTO   </title>        
<urlsolve>https://www.youtube.com/watch?v=kOpH6kKKHHw</urlsolve>
<thumbnail>http://2.bp.blogspot.com/_ug5srv4OwuQ/TCt1FxiN-OI/AAAAAAAAC40/XPA67n8Je4g/s1600/CoverIngrid2010.jpg</thumbnail>
<fanart>https://i.ytimg.com/vi/79zLuiURsM0/maxresdefault.jpg</fanart>
</item>

<item>
<title>Concierto Christine D'Clario - CaChristine D'Clario | Eterno Live | DVD Completo   </title>        
<urlsolve>https://www.youtube.com/watch?v=WTD_MvI92fw</urlsolve>
<thumbnail>http://vidaenaccionradio.com/wp-content/uploads/2016/05/Christine-D%E2%80%99Clario_Eterno-Live_3.jpg</thumbnail>
<fanart>http://puntocristiano.co/wp-content/uploads/2016/01/Christine-D%C2%B4Clario-Punto-Cristiano-1-1200x900.jpg</fanart>
</item>

<item>
<title>2017 MARCELA GANDARA CONCIERTO COMPLETO  </title>        
<urlsolve>https://www.youtube.com/watch?v=cJYP-dSV5-A</urlsolve>
<thumbnail>http://4.bp.blogspot.com/-xYc-r3iIfZc/UKOd556vc5I/AAAAAAAAEOg/eKOKWXgW62c/s1600/Cover_MarcelaGandaraFeatV2+copia.jpg</thumbnail>
<fanart>http://cdn.cristiana.fm/artists/m/marcela-gandara/marcela-gandara-6.jpg</fanart>
</item>

<item>
<title>ratt [full set] live at sherman theater in stroudsburg, pa 4.28.17   </title>        
<urlsolve>https://www.youtube.com/watch?v=tuiEaoFwRMo</urlsolve>
<thumbnail>https://i.pinimg.com/originals/61/cd/f9/61cdf9317d4bf3fd5b6e096bcb21610a.png</thumbnail>
<fanart>http://assets.blabbermouth.net.s3.amazonaws.com/media/rattreinvasiontourbigger_638.jpg</fanart>
</item>

<item>
<title>Winger ! Complete Set ! Monsters or Rock Cruise 2017 Live  </title>        
<urlsolve>https://www.youtube.com/watch?v=MorV-PQBU24</urlsolve>
<thumbnail>https://rockstaruniversity.com/wp-content/uploads/2016/10/winger-425x306.png</thumbnail>
<fanart>https://sc-schemes.s3.amazonaws.com/10959/header_image.jpg</fanart>
</item>

<item>
<title>Stryper - Tim Gaines last show !Complete Set! Monsters of Rock Cruise 2017 LIVE Pool Stage  </title>        
<urlsolve>https://www.youtube.com/watch?v=UfydACljdCc</urlsolve>
<thumbnail>http://www.theglobaldispatch.com/wp-content/uploads/2013/10/Stryper-band-photo.png</thumbnail>
<fanart>http://www.fullaccessmagazine.com/sites/default/files/images/stryper.jpg</fanart>
</item>

<item>
<title>DVD Stryper - Live in Indonésia - Full  </title>        
<urlsolve>https://www.youtube.com/watch?v=dGi1xKhqlFg</urlsolve>
<thumbnail>https://firestreamvault.com/rateimages/band_122_logo_6.png</thumbnail>
<fanart>http://www.jesusfreakhideout.com/news/2012/08/pics/stryperlive.jpg</fanart>
</item>

<item>
<title>Poison - Swallow This Live 1991 [Full Concert]    </title>        
<urlsolve>https://www.youtube.com/watch?v=4o7ptRSf04g</urlsolve>
<thumbnail>http://fitfabforty.com/wp-content/uploads/2015/04/poison.png</thumbnail>
<fanart>http://www.standupinternational.com/images/Poison_3.jpg</fanart>
</item>

<item>
<title>Poison: Live Raw & Uncut [Full Concert]  </title>        
<urlsolve>https://www.youtube.com/watch?v=CFNlFgstXb4</urlsolve>
<thumbnail>https://metallicide.com/images/categories/Poison-logo.png</thumbnail>
<fanart>http://i599.photobucket.com/albums/tt73/lonely_planet_girl/bands/Poison-Band.jpg</fanart>
</item>

<item>
<title>Motley Crue - May 29, 1983 - San Bernardino, CA  </title>        
<urlsolve>https://www.youtube.com/watch?v=jh8Zh7SdMVs</urlsolve>
<thumbnail>http://www.logotypes101.com/logos/92/3CA2310281D5094C9E8672594F80ACCA/mc.png</thumbnail>
<fanart>http://www.metalinsider.net/site/wp-content/uploads/2016/11/Motley-Crue-1024x538.jpg</fanart>
</item>

<item>
<title>Cinderella - Live in Detroit 1991 [Full Concert]   </title>        
<urlsolve>https://www.youtube.com/watch?v=WRyyTit6cgw</urlsolve>
<thumbnail>https://fanart.tv/fanart/music/8b07bb3d-aff5-4ce5-9f41-2872bc79320f/hdmusiclogo/cinderella-504071677ef98.png</thumbnail>
<fanart>https://i.pinimg.com/originals/e6/0f/41/e60f41dff3b0e42c3e7198aa91e18318.jpg</fanart>
</item>

<item>
<title>Firehouse - Trixter - Live In Lafayette, LA 1991 [Full Concert]   </title>        
<urlsolve>https://www.youtube.com/watch?v=I2N0tB3Fay4</urlsolve>
<thumbnail>https://fanart.tv/fanart/music/3ca0ef91-3297-4ef8-a99a-1c1a54dc8ac7/hdmusiclogo/firehouse-5281798fafffd.png</thumbnail>
<fanart>http://moondancejam.com/img/bands/16-Firehouse.jpg</fanart>
</item>

<item>
<title>Warrant - Live In Lafayette, LA 1991[Full Concert]   </title>        
<urlsolve>https://www.youtube.com/watch?v=6cCR3Q17egs</urlsolve>
<thumbnail>https://metallicide.com/images/categories/warrant-logo.png</thumbnail>
<fanart>https://www.kamloopsbcnow.com/files/warrant1.jpg</fanart>
</item>

<item>
<title>White Lion - Live At The Ritz, NYC, 1988 [Full Concert]    </title>        
<urlsolve>https://www.youtube.com/watch?v=-DqVqtwIz0o</urlsolve>
<thumbnail>https://fanart.tv/fanart/music/4fe426de-9c86-46d5-bbab-239f5e7344bf/hdmusiclogo/white-lion-526aec3a1f269.png</thumbnail>
<fanart>https://i.ytimg.com/vi/p81M7O7Hemo/maxresdefault.jpg</fanart>
</item>

<item>
<title>Europe - Live at Wacken Open Air 2015 (HD)   </title>        
<urlsolve>https://www.youtube.com/watch?v=voyrL1Jm0ew</urlsolve>
<thumbnail>http://www.adrenalinepr.com/wp-content/uploads/2015/01/europe_logo.png</thumbnail>
<fanart>http://www.gbc.gi/uploads/news/491JC_dgag.jpg</fanart>
</item>

<item>
<title>Scorpions Live Saarbrücken Full Concert 1080p HD    </title>        
<urlsolve>https://www.youtube.com/watch?v=wtx5jiDEvJc</urlsolve>
<thumbnail>http://4.bp.blogspot.com/-8lBa99vJEB4/UfMQ0IHfszI/AAAAAAAAIOs/inX8-0Efqh0/s1600/scorpions-logotipo.png</thumbnail>
<fanart>http://1.bp.blogspot.com/-ixqtw_FNhLI/UOujBqPJgmI/AAAAAAAAhKQ/cj0jGvUOx7Y/s1600/Scorpions+Final+Sting+Tour.jpg</fanart>
</item>

<item>
<title>Def Leppard - Live in Sheffield 1993 [Full Concert]    </title>        
<urlsolve>https://www.youtube.com/watch?v=JJWH-RCy-y8</urlsolve>
<thumbnail>http://defleppard.primarywave.netdna-cdn.com/wp-content/themes/def/images/logo.png</thumbnail>
<fanart>http://www.billboard.com/files/stylus/2458059-def-leppard-eighties-617-409.jpg</fanart>
</item>

<item>
<title>DOKKEN - Anaheim, California - November 4, 1999 with Reb Beach Erase The Slate Tour Live  </title>        
<urlsolve>https://www.youtube.com/watch?v=GAHGiVsk9ek</urlsolve>
<thumbnail>http://www.eximagenes.com/Zfg.png</thumbnail>
<fanart>https://i.gse.io/gse_media/116/7/1472600098-dokken-tickets.jpg?h=520&p=1&q=60&w=920&c=1</fanart>
</item>

<item>
<title>Whitesnake - Live In The Still Of The Night ] [XviD].HD    </title>        
<urlsolve>https://www.youtube.com/watch?v=JO77qrULPWk</urlsolve>
<thumbnail>http://www.hallowed.se/Images/logos/whitesnake_logo.png</thumbnail>
<fanart>http://assets.blabbermouth.net.s3.amazonaws.com/media/whitesnake2015lineupwlogo_638.jpg</fanart>
</item>

<item>
<title>Mr Big - ☆ Live in San Francisco 1992 ☆ Full    </title>        
<urlsolve>https://www.youtube.com/watch?v=2xc345erF1k</urlsolve>
<thumbnail>http://fantoons.tv/wp-content/uploads/2015/11/MR.-BIG-logo21-360x300.png</thumbnail>
<fanart>http://media.washtimes.com.s3.amazonaws.com/media/image/2017/07/20/big.jpg</fanart>
</item>

<item>
<title>Yngwie J. Malmsteen - Trial by Fire - Live in Leningrad (1989) - HQ    </title>        
<urlsolve>https://www.youtube.com/watch?v=lbg8g48mU5s</urlsolve>
<thumbnail>https://rockcinema.eu/resources/yniwi3e3e.png</thumbnail>
<fanart>http://thehub.musiciansfriend.com/images/interviews/yngwie-malmsteen-onstage-665x475.jpg</fanart>
</item>

<item>
<title>Van Halen - Live in New Haven's Veterans Memorial Coliseum 1986 [Full Concert]    </title>        
<urlsolve>https://www.youtube.com/watch?v=wIWLNBPS2r8</urlsolve>
<thumbnail>https://defendingaxlrose.files.wordpress.com/2015/03/screen-shot-2015-03-25-at-5-25-44-pm.png</thumbnail>
<fanart>http://www.classicrockreview.com/wp-content/uploads/2016/03/VanHalen-1986.jpg</fanart>
</item>

<item>
<title>Bon Jovi Live 2017 Full Concert   </title>        
<urlsolve>https://www.youtube.com/watch?v=kg1z2_vx_X8</urlsolve>
<thumbnail>http://www.wplr.com/Pics/Hall%20of%20Fame/bonjovi.png</thumbnail>
<fanart>http://ultimateclassicrock.com/files/2014/11/Stuart-Wilson-630x420.jpg</fanart>
</item>

<item>
<title>Aerosmith - Live In Detroit - 9/9/14 - ProShot   </title>        
<urlsolve>https://www.youtube.com/watch?v=neFgnugwc14</urlsolve>
<thumbnail>http://orig01.deviantart.net/fb46/f/2009/183/b/b/revamped_aerosmith_logo_by_xenyph.png</thumbnail>
<fanart>http://bestclassicbands.com/wp-content/uploads/2016/04/aerosmith-fb.jpg</fanart>
</item>

<item>
<title>   </title>        
<urlsolve></urlsolve>
<thumbnail></thumbnail>
<fanart></fanart>
</item>

<item>
<title>   </title>        
<urlsolve></urlsolve>
<thumbnail></thumbnail>
<fanart></fanart>
</item>

<item>
<title>   </title>        
<urlsolve></urlsolve>
<thumbnail></thumbnail>
<fanart></fanart>
</item>

<item>
<title>   </title>        
<urlsolve></urlsolve>
<thumbnail></thumbnail>
<fanart></fanart>
</item>