<?xml version="1.0" encoding="UTF-8" standalone="yes"?>

<item>
<title>Programa Especial: "Detrás de la Promesa" (Parte 1)</title>        
<urlsolve>https://www.youtube.com/watch?v=XczwnoVl3pY</urlsolve>
<thumbnail>https://i.ytimg.com/vi/H8OqpazdZEg/hqdefault.jpg</thumbnail>
<fanart>https://1.bp.blogspot.com/-PtmLWpgsYNc/Wy9PPKmXBDI/AAAAAAAAAUk/dCS6WrQtaIESlMDr6Rp9oJIIGtUJ88NzACLcBGAs/s1600/IMG_4185.JPG</fanart>
</item>

<item>
<title>Programa Especial: "Detrás de la Promesa" (Parte 2)</title>        
<urlsolve>https://www.youtube.com/watch?v=myd26dqws2s</urlsolve>
<thumbnail>http://assets.gfrvideo.com/end/2018/06/29/248137_20180629135720_detras-de-la-ley-promesa-programa-especial/still_0003.jpg</thumbnail>
<fanart>https://1.bp.blogspot.com/-PtmLWpgsYNc/Wy9PPKmXBDI/AAAAAAAAAUk/dCS6WrQtaIESlMDr6Rp9oJIIGtUJ88NzACLcBGAs/s1600/IMG_4185.JPG</fanart>
</item>

<item>
<title>¿Qué es la Junta de Control Fiscal?</title>        
<urlsolve>https://www.youtube.com/watch?v=IFVQbAbTp7Y</urlsolve>
<thumbnail>http://www.radioisla1320.com/wp-content/uploads/2016/11/Junta-de-Control-Fiscal.jpg</thumbnail>
<fanart>http://2.bp.blogspot.com/-99-TBbAQwtU/VmuPxFGQ1PI/AAAAAAAAdHE/DLyPWHw0SZA/s1600/12362757_1263431313682322_4379683046389811337_o.jpg</fanart>
</item>

<item>
<title>Programas reportajes especiales de PR</title>
<thumbnail>https://rec-eph.primerahora.com/images/tnph3/615/304/1/1/615/304/2018/02/07/normando-ahi-esta-la-verdad.jpg</thumbnail>
<fanart>https://i.ytimg.com/vi/n6YzC8IClCM/maxresdefault.jpg</fanart>
<link>http://ignoreme</link>
<externallink>https://raw.githubusercontent.com/pepe-01/Bluwy-TV/master/ReportajesEspecialesPR.xml</externallink>
</item>

<item>
<title>Obsolescencia programada</title>        
<urlsolve>https://www.youtube.com/watch?v=9ATvsD-or-o</urlsolve>
<thumbnail>https://static1.elcomercio.es/www/multimedia/201707/15/media/cortadas/obsolecencia-programada-kWS-U40356710212eYE-624x385@El%20Comercio.jpg</thumbnail>
<fanart>https://magazine.previsorabilbaina.com//wp-content/uploads/2015/12/obsolescencia_programada.jpg</fanart>
</item>

<item>
<title>EL Cambio climático YA ESTA AQUI, DOCUMENTALES, CAMBIO CLIMATICO</title>        
<urlsolve>https://www.youtube.com/watch?v=EC8UCAWpGHE</urlsolve>
<thumbnail>https://img.youtube.com/vi/ifrHogDujXw/0.jpg</thumbnail>
<fanart></fanart>
</item>

<item>
<title>¿Qué esta pasando con el clima? Documental completo BBC</title>        
<urlsolve>https://www.youtube.com/watch?v=Ysxl_mZhe5g</urlsolve>
<thumbnail>https://img.youtube.com/vi/ifrHogDujXw/0.jpg</thumbnail>
<fanart></fanart>
</item>

<item>
<title>Casas del futuro - Soñar el futuro</title>        
<urlsolve>https://www.youtube.com/watch?v=IG45p-OqEXI</urlsolve>
<thumbnail>https://i.ytimg.com/vi/IG45p-OqEXI/hqdefault.jpg</thumbnail>
<fanart>https://st3.idealista.com/news/archivos/2017-01/hogar_inteligente.jpg?sv=Okt972IF</fanart>
</item>

<item>
<title>Vida cotidiana | 2111 l Discovery Latinoamérica</title>        
<urlsolve>https://www.youtube.com/watch?v=gbK-kXCFnv8</urlsolve>
<thumbnail>https://i.ytimg.com/vi/JLRCf6AjWj8/hqdefault.jpg</thumbnail>
<fanart>https://i.ytimg.com/vi/gbK-kXCFnv8/maxresdefault.jpg</fanart>
</item>

<item>
<title>LA CIUDAD PERFECTA. EL FUTURO por Stephen Hawking Documental HD</title>        
<urlsolve>https://www.youtube.com/watch?v=VCv_WiyopVA</urlsolve>
<thumbnail>https://i.ytimg.com/vi/oD4M_iU_k14/hqdefault.jpg</thumbnail>
<fanart>https://i.ytimg.com/vi/VCv_WiyopVA/maxresdefault.jpg</fanart>
</item>

<item>
<title>¿El viaje en el tiempo es posible? Secretos del universo T1</title>        
<urlsolve>https://www.youtube.com/watch?v=6KHRuXeMaos</urlsolve>
<thumbnail>https://i.imgur.com/pc1N5q7.jpg</thumbnail>
<fanart>https://i.ytimg.com/vi/n2rtpFTLZTc/maxresdefault.jpg</fanart>
</item>

<item>
<title>Maestros de la ingeniera 1- Construir cada vez mas altos</title>        
<urlsolve>https://www.youtube.com/watch?v=38UM1TBu1Rk</urlsolve>
<thumbnail>https://images.adsttc.com/media/images/5a8c/38a5/f197/cce9/dc00/004c/newsletter/Skyscrapers5.jpg?1519138975</thumbnail>
<fanart>https://i.ytimg.com/vi/38UM1TBu1Rk/maxresdefault.jpg</fanart>
</item>

<item>
<title>MegaFactorias - Boeing 747 800</title>        
<urlsolve>https://www.youtube.com/watch?v=sCURi4FehRY</urlsolve>
<thumbnail>http://www.lakyfilms.com/Resources/Fotos/Boeing7478-1(0).jpg</thumbnail>
<fanart>https://i.ytimg.com/vi/Ju-Fj1dgtFE/maxresdefault.jpg</fanart>
</item>

<item>
<title>Megafabricas / AMG Mercedes (Discovery Turbo)</title>        
<urlsolve>https://www.youtube.com/watch?v=_iOxqo1cVNk</urlsolve>
<thumbnail>https://i.ytimg.com/vi/Z7nVqWp8jyo/hqdefault.jpg</thumbnail>
<fanart>https://i.ytimg.com/vi/fEOvE7oACQ0/maxresdefault.jpg</fanart>
</item>

<item>
<title>Megafabricas / CAMARO SS (Discovery Turbo)</title>        
<urlsolve>https://www.youtube.com/watch?v=J4nzPFAM0mo</urlsolve>
<thumbnail>https://i.ytimg.com/vi/J4nzPFAM0mo/hqdefault.jpg</thumbnail>
<fanart>https://i.ytimg.com/vi/98BnxPu7rdM/maxresdefault.jpg</fanart>
</item>

<item>
<title>Megafactorias - Chevrolet Camaro</title>        
<urlsolve>https://www.youtube.com/watch?v=84fXwxph4q0</urlsolve>
<thumbnail>http://i59.fastpic.ru/big/2013/1113/6c/a2fc721aa8d294e1e2e99720032a276c.jpg</thumbnail>
<fanart>http://es.chevrolet.com/content/dam/chevrolet/na/us/english/index/articles/camaro-life/camaro-ss/01-images/2017-camaro-ss-01.jpg?imwidth=1200</fanart>
</item>

<item>
<title>Megafabricas - **Ford Mustang</title>        
<urlsolve>https://www.youtube.com/watch?v=4EE72GYnI5A</urlsolve>
<thumbnail>https://documentalesmx.files.wordpress.com/2012/10/superautosmustang.jpg</thumbnail>
<fanart>https://i.ytimg.com/vi/sqDdTPuKc-A/maxresdefault.jpg</fanart>
</item>

<item>
<title>Megafabricas **Corvette ZR</title>        
<urlsolve>https://www.youtube.com/watch?v=hl5H-vED1dM</urlsolve>
<thumbnail>https://i.pinimg.com/originals/44/b2/67/44b267bda109fd42627ed1aafc27f492.jpg</thumbnail>
<fanart>https://i.ytimg.com/vi/Cvq_Xlz-VBE/maxresdefault.jpg</fanart>
</item>

<item>
<title>Megafactorias - Dodge Challenger</title>        
<urlsolve>https://www.youtube.com/watch?v=tbKnDXlzNZs</urlsolve>
<thumbnail>https://i.ytimg.com/vi/kYw2FCXBRfM/hqdefault.jpg</thumbnail>
<fanart>https://i.ytimg.com/vi/tbKnDXlzNZs/maxresdefault.jpg</fanart>
</item>

<item>
<title>Megafactorias Lamborghini Aventador (National Geographic)</title>        
<urlsolve>https://www.youtube.com/watch?v=JDzdySMoLkA</urlsolve>
<thumbnail>https://i.pinimg.com/originals/4a/f4/52/4af452c4576eb6754947a2869def85eb.jpg</thumbnail>
<fanart>https://i.ytimg.com/vi/bDWUZl_RITA/maxresdefault.jpg</fanart>
</item>

<item>
<title>Mega Fabricas - Aston Martin One 77 (National Geographic)</title>        
<urlsolve>https://www.youtube.com/watch?v=H6oOt_luBVc</urlsolve>
<thumbnail>https://i.ytimg.com/vi/O0KGS1RyB-U/hqdefault.jpg</thumbnail>
<fanart>https://i.ytimg.com/vi/H6oOt_luBVc/maxresdefault.jpg</fanart>
</item>

<item>
<title>Mega fabricas - fabricando el porche 911 (National Geographic)</title>        
<urlsolve>https://www.youtube.com/watch?v=uuUoKh3X5fE</urlsolve>
<thumbnail>https://i.ytimg.com/vi/8vyGw8sZ7Rw/hqdefault.jpg</thumbnail>
<fanart>https://www.nationalgeographic.es/sites/spain/files/styles/desktop/public/11020.600x450.jpg?itok=ybkEM-VN</fanart>
</item>

<item>
<title>MegaFábricas NatGeo Coca Cola</title>        
<urlsolve>https://www.youtube.com/watch?v=oNjtA7WVKuk</urlsolve>
<thumbnail>https://lh5.googleusercontent.com/-u3I9yW4jupk/ToKCBm5AmSI/AAAAAAAABZc/9kClQetrwdM/s1600/banncocacola.jpg</thumbnail>
<fanart>https://i.ytimg.com/vi/J8voFoBN_5Q/maxresdefault.jpg</fanart>
</item>

<item>
<title>Megafactorias Lego HD</title>        
<urlsolve>https://www.youtube.com/watch?v=SWpANSAgAa4</urlsolve>
<thumbnail>http://dokonline.com/uploads/posts/2014-04/1396593906_1.jpg</thumbnail>
<fanart>https://natgeo.imgix.net/factsheets/thumbnails/LEGOfacts_legomanandbricks.jpg?auto=compress,format&w=1600&h=900&fit=crop</fanart>
</item>

<item>
<title>Las Megafabricas mas Grandes del Mundo Documental (2017)</title>        
<urlsolve>https://www.youtube.com/watch?v=G7eRklPcptY</urlsolve>
<thumbnail>https://i.ytimg.com/vi/9Hym8z7HH2g/hqdefault.jpg</thumbnail>
<fanart>https://i.ytimg.com/vi/ukdc8oVyEYg/maxresdefault.jpg</fanart>
</item>

<item>
<title>MegaFactorias - Jet Privado Learjet 60XR</title>        
<urlsolve>https://www.youtube.com/watch?v=5Qsg2RUTNn8</urlsolve>
<thumbnail>https://i.ytimg.com/vi/sTWktJmZBWc/hqdefault.jpg</thumbnail>
<fanart>https://i.ytimg.com/vi/5Qsg2RUTNn8/maxresdefault.jpg</fanart>
</item>

<item>
<title>Megafactorias - Caterpillar</title>        
<urlsolve>https://www.youtube.com/watch?v=ueCfKZfBpE0</urlsolve>
<thumbnail>https://i.ytimg.com/vi/LSgu69zewBo/hqdefault.jpg</thumbnail>
<fanart>http://3.bp.blogspot.com/-VTTX3HNuchs/UtFg6WRuAnI/AAAAAAAABl0/fcddIBGYWMo/w1200-h630-p-k-no-nu/CATERPILLAR+CAT+988K+TONKIN+5.jpg</fanart>
</item>

<item>
<title>Documental - Exceso de poblacion</title>        
<urlsolve>https://www.youtube.com/watch?v=MknHYs2RnDU</urlsolve>
<thumbnail>https://i.ytimg.com/vi/uYPfAIznUak/hqdefault.jpg</thumbnail>
<fanart>http://img2.rtve.es/v/3938056/</fanart>
</item>

<item>
<title>Los Secretos Mejor Guardados de U S A Documental completo</title>        
<urlsolve>https://www.youtube.com/watch?v=NEB4brxK6dQ</urlsolve>
<thumbnail>https://i.ytimg.com/vi/Wcj20WG_MkI/hqdefault.jpg</thumbnail>
<fanart>https://www.army.mil/e2/c/images/2016/10/14/453858/original.jpg</fanart>
</item>

<item>
<title>Ciudades Bajo Tierra 22 de 27 Las Bases Secretas Sovieticas</title>        
<urlsolve>https://www.youtube.com/watch?v=g2Ro1nacfMs</urlsolve>
<thumbnail>http://m1.paperblog.com/i/193/1935853/ciudades-tierra-L-NHNsWh.jpeg</thumbnail>
<fanart>https://vistoenlaweb.files.wordpress.com/2012/10/ciudadessubterraneas.jpg</fanart>
</item>

<item>
<title>11-Septiembre El día que cambió el mundo Documental</title>        
<urlsolve>https://www.youtube.com/watch?v=PMJDPgf-P1s</urlsolve>
<thumbnail>https://www.factslides.com/imgs/911-planes.jpg</thumbnail>
<fanart></fanart>
</item>

<item>
<title>La Verdadera Historia de las Torres Gemelas</title>        
<urlsolve>https://www.youtube.com/watch?v=auwg9VdE0uw</urlsolve>
<thumbnail>https://www.factslides.com/imgs/911-planes.jpg</thumbnail>
<fanart></fanart>
</item>

<item>
<title>Masones - La Sociedad más Secreta del Mundo</title>        
<urlsolve>https://www.youtube.com/watch?v=J2zqbuLtB64</urlsolve>
<thumbnail>https://www.ebookscatolicos.com/wp-content/uploads/2015/04/Los-masones.jpg</thumbnail>
<fanart>https://i.ytimg.com/vi/OBYaRokRex4/maxresdefault.jpg</fanart>
</item>

<item>
<title>Secretos De Illuminatis y Masones, El Poder Oculto</title>        
<urlsolve>https://www.youtube.com/watch?v=VfLZA1edO4s</urlsolve>
<thumbnail>http://www.sjgames.com/inwo/artwork/back1.gif</thumbnail>
<fanart></fanart>
</item>

<item>
<title>El billete de 1 dolar y sus secretos más sorprendentes</title>        
<urlsolve>https://www.youtube.com/watch?v=f1ztUwqVYoE</urlsolve>
<thumbnail>https://i1.wp.com/www.garylellis.org/wp-content/uploads/2014/09/one-dollar-bills-8875868.jpg</thumbnail>
<fanart></fanart>
</item>

<item>
<title>Narco Tecnologia</title>        
<urlsolve>https://www.youtube.com/watch?v=l0GGjvyOUho</urlsolve>
<thumbnail>http://2.bp.blogspot.com/-MbC5RzPrSwk/UMPZjQqMEvI/AAAAAAAAC_g/bHE7dH1ldUM/s1600/african_narco_news_cocaine_narco_technology_3.jpg</thumbnail>
<fanart></fanart>
</item>

<item>
<title>Narco Armas un documental de Discovery Chanel</title>        
<urlsolve>https://www.youtube.com/watch?v=iJ_uXt68sVs</urlsolve>
<thumbnail>http://2.bp.blogspot.com/_FepxIa52Sgk/SawlQWsGi9I/AAAAAAAAA-g/x1dcY1_jmQg/s400/Armas.jpg</thumbnail>
<fanart></fanart>
</item>

<item>
<title>EXISTIÓ OTRA CIVILIZACIÓN - ALGO NO ENCAJA EN LA HISTORIA</title>        
<urlsolve>https://www.youtube.com/watch?v=5_3DzrXHDuY</urlsolve>
<thumbnail>http://slideplayer.es/12/3583780/big_thumb.jpg</thumbnail>
<fanart></fanart>
</item>

<item>
<title>Adam Savage - Podemos ser inmortales?</title>        
<urlsolve>https://vimeo.com/165579670</urlsolve>
<thumbnail>https://ugc.kn3.net/i/760x/https://lh4.googleusercontent.com/-3nl-S2h1HLM/TwqinyDGRGI/AAAAAAAAB0E/B_KmUE2d3Fg/s1600/bannc11.jpg</thumbnail>
<fanart>https://i.vimeocdn.com/video/569484073_960.jpg</fanart>
</item>

<item>
<title>Camino a la inmortalidad</title>        
<urlsolve>https://www.youtube.com/watch?v=B5yy3Lf2684</urlsolve>
<thumbnail>https://i.ytimg.com/vi/2eQFUNbEBhk/hqdefault.jpg</thumbnail>
<fanart>http://www.ovideo.com/media/uploads/trabajos/savater-1.jpg</fanart>
</item>

<item>
<title>Los inmortales (DOCUMENTAL COMPLETO)</title>        
<urlsolve>https://www.youtube.com/watch?v=KSvhBmthNEA</urlsolve>
<thumbnail>https://i.ytimg.com/vi/KSvhBmthNEA/hqdefault.jpg</thumbnail>
<fanart></fanart>
</item>

<item>
<title>'Generación perdida' - Documental de RT sobre la vida de los refugiados sirios</title>        
<urlsolve>https://www.youtube.com/watch?v=R1lK-HkScYk</urlsolve>
<thumbnail>https://i.ytimg.com/vi/fUcIM5ZiVWc/hqdefault.jpg</thumbnail>
<fanart>https://i.ytimg.com/vi/R1lK-HkScYk/maxresdefault.jpg</fanart>
</item>

<item>
<title>Trenes extremos, EL TREN DE HIELO</title>        
<urlsolve>https://www.youtube.com/watch?v=HldMC0WHfZM</urlsolve>
<thumbnail>https://i.ytimg.com/vi/2Wmgnv3o2yM/hqdefault.jpg</thumbnail>
<fanart>http://www.lugaresdenieve.com/sites/default/files/estaciones/jungfrau3.jpg</fanart>
</item>

<item>
<title>Mega Trenes / JAPÓN (Tren Bala)</title>        
<urlsolve>https://www.youtube.com/watch?v=b2aS5yiWhJY</urlsolve>
<thumbnail>https://i.ytimg.com/vi/prHEzOsp2dU/hqdefault.jpg</thumbnail>
<fanart>https://i.ytimg.com/vi/nMYqkVmCxpc/maxresdefault.jpg</fanart>
</item>

<item>
<title>Mega Trenes / ALEMANIA (Maglev: Tren del Futuro)</title>        
<urlsolve>https://www.youtube.com/watch?v=qn2yx5CMSMY</urlsolve>
<thumbnail>https://i.ytimg.com/vi/c1C9P4hbXyg/hqdefault.jpg</thumbnail>
<fanart>https://hipertextual.com/files/2015/04/Maglev_train.jpg</fanart>
</item>

<item>
<title>Selva tropical Flora y Fauna. Documentales National Geographic</title>        
<urlsolve>https://www.youtube.com/watch?v=3gHJxw_1hsQ</urlsolve>
<thumbnail>https://i.ytimg.com/vi/YT56dYCgE-Y/hqdefault.jpg</thumbnail>
<fanart>https://i.ytimg.com/vi/yYTYQAkziG0/maxresdefault.jpg</fanart>
</item>

<item>
<title>El planeta bajo el agua / LOS GIGANTES DEL MAR</title>        
<urlsolve>https://www.youtube.com/watch?v=kYrNtsIZu1Y</urlsolve>
<thumbnail>https://i.ytimg.com/vi/gAAEpCQkqRw/hqdefault.jpg</thumbnail>
<fanart>https://i.ytimg.com/vi/JFBFvqXOZSs/maxresdefault.jpg</fanart>
</item>

<item>
<title>EL ARRECIFE SECRETO DE CUBA | Nat Geo Wild</title>        
<urlsolve>https://www.youtube.com/watch?v=eI-8Gg1HDew</urlsolve>
<thumbnail>https://i.ytimg.com/vi/KuxdW0nEEO0/hqdefault.jpg</thumbnail>
<fanart>https://i.ytimg.com/vi/k9CKn9209dY/maxresdefault.jpg</fanart>
</item>

<item>
<title></title>        
<urlsolve></urlsolve>
<thumbnail></thumbnail>
<fanart></fanart>
</item>

<item>
<title></title>        
<urlsolve></urlsolve>
<thumbnail></thumbnail>
<fanart></fanart>
</item>

<item>
<title></title>        
<urlsolve></urlsolve>
<thumbnail></thumbnail>
<fanart></fanart>
</item>

<item>
<title></title>        
<urlsolve></urlsolve>
<thumbnail></thumbnail>
<fanart></fanart>
</item>

<item>
<title></title>        
<urlsolve></urlsolve>
<thumbnail></thumbnail>
<fanart></fanart>
</item>


