<?xml version="1.0" encoding="UTF-8" standalone="yes"?>

<item>
<title>Dra. Mamá - Lcda.Sara Tolosa - Centro para Puerto Rico</title>        
<urlsolve>https://www.youtube.com/watch?v=J6tkWGMsp_k&t=4s</urlsolve>
<thumbnail>https://i.ytimg.com/vi/VVB3ECCocdg/hqdefault.jpg</thumbnail>
<fanart>http://www.heldahoy.com/wp-content/uploads/2014/12/DRA-MAMA.jpg</fanart>
</item>

<item>
<title>Dra Mamá - Jefas de familias</title>        
<urlsolve>https://www.youtube.com/watch?v=GW-F9AQcyoY</urlsolve>
<thumbnail>https://i.ytimg.com/vi/VVB3ECCocdg/hqdefault.jpg</thumbnail>
<fanart>http://www.heldahoy.com/wp-content/uploads/2014/12/DRA-MAMA.jpg</fanart>
</item>

<item>
<title>Dra. Mamá - Lactancia</title>        
<urlsolve>https://www.youtube.com/watch?v=CIfyfH1MG-Y</urlsolve>
<thumbnail>https://i.ytimg.com/vi/VVB3ECCocdg/hqdefault.jpg</thumbnail>
<fanart>http://www.heldahoy.com/wp-content/uploads/2014/12/DRA-MAMA.jpg</fanart>
</item>

<item>
<title>Dra Mamá - La Trombofilia</title>        
<urlsolve>https://www.youtube.com/watch?v=REOajULHo0g</urlsolve>
<thumbnail>https://i.ytimg.com/vi/VVB3ECCocdg/hqdefault.jpg</thumbnail>
<fanart>http://www.heldahoy.com/wp-content/uploads/2014/12/DRA-MAMA.jpg</fanart>
</item>

<item>
<title>Dra. Mamá - Grace Fontecha - Entrenadora de modelos</title>        
<urlsolve>https://www.youtube.com/watch?v=6Twt3drdaNQ</urlsolve>
<thumbnail>https://i.ytimg.com/vi/VVB3ECCocdg/hqdefault.jpg</thumbnail>
<fanart>http://www.heldahoy.com/wp-content/uploads/2014/12/DRA-MAMA.jpg</fanart>
</item>
