<?xml version="1.0" encoding="UTF-8" standalone="yes"?>

<item>
<title>Cap 1</title>        
<urlsolve></urlsolve>
<thumbnail></thumbnail>
<fanart></fanart>
</item>

<item>
<title>Cap 2</title>        
<urlsolve></urlsolve>
<thumbnail></thumbnail>
<fanart></fanart>
</item>

<item>
<title>Cap 3</title>        
<urlsolve></urlsolve>
<thumbnail></thumbnail>
<fanart></fanart>
</item>

<item>
<title>Cap 4</title>        
<urlsolve></urlsolve>
<thumbnail></thumbnail>
<fanart></fanart>
</item>

<item>
<title>Cap 5</title>        
<urlsolve></urlsolve>
<thumbnail></thumbnail>
<fanart></fanart>
</item>

<item>
<title>MURCHISON-HUME / T-4 / Cap 6</title>        
<urlsolve>http://www.dailymotion.com/video/x5ompdw</urlsolve>
<thumbnail>http://www.cineymas.com.ar/wp-content/uploads/2017/04/History-El-Socio-Marcus-Lemonis-1-660x460.jpg</thumbnail>
<fanart>https://elalebrijeudl.files.wordpress.com/2018/03/tv_pit05_q5203_0038.jpg?w=1200</fanart>
</item>

<item>
<title>Cap 7</title>        
<urlsolve></urlsolve>
<thumbnail></thumbnail>
<fanart></fanart>
</item>

<item>
<title>Cap 8</title>        
<urlsolve></urlsolve>
<thumbnail></thumbnail>
<fanart></fanart>
</item>

<item>
<title>Suministros de Cocina Bowery Marcus Lemonis / T-4 / Cap 9</title>        
<urlsolve>http://www.dailymotion.com/video/x61ih4g</urlsolve>
<thumbnail>http://www.cineymas.com.ar/wp-content/uploads/2017/04/History-El-Socio-Marcus-Lemonis-1-660x460.jpg</thumbnail>
<fanart>https://elalebrijeudl.files.wordpress.com/2018/03/tv_pit05_q5203_0038.jpg?w=1200</fanart>
</item>

<item>
<title>Cap 10</title>        
<urlsolve></urlsolve>
<thumbnail></thumbnail>
<fanart></fanart>
</item>

<item>
<title>"SUSANA MONACO” Marcus Lemonis / T-4 / Cap 11</title>        
<urlsolve>http://www.dailymotion.com/video/x61i3m8</urlsolve>
<thumbnail>http://www.cineymas.com.ar/wp-content/uploads/2017/04/History-El-Socio-Marcus-Lemonis-1-660x460.jpg</thumbnail>
<fanart>https://elalebrijeudl.files.wordpress.com/2018/03/tv_pit05_q5203_0038.jpg?w=1200</fanart>
</item>

<item>
<title>Cap 12</title>        
<urlsolve></urlsolve>
<thumbnail></thumbnail>
<fanart></fanart>
</item>

<item>
<title>Cap 13</title>        
<urlsolve></urlsolve>
<thumbnail></thumbnail>
<fanart></fanart>
</item>

<item>
<title>Productos Caplares Español Marcus Lemonis / T-4 / Cap 14</title>        
<urlsolve>http://www.dailymotion.com/video/x69xjej</urlsolve>
<thumbnail>http://www.cineymas.com.ar/wp-content/uploads/2017/04/History-El-Socio-Marcus-Lemonis-1-660x460.jpg</thumbnail>
<fanart>https://elalebrijeudl.files.wordpress.com/2018/03/tv_pit05_q5203_0038.jpg?w=1200</fanart>
</item>

<item>
<title>Armonia Acustica Español Marcus Lemonis / T-4 / Cap 15</title>        
<urlsolve>http://www.dailymotion.com/video/x69xjei</urlsolve>
<thumbnail>http://www.cineymas.com.ar/wp-content/uploads/2017/04/History-El-Socio-Marcus-Lemonis-1-660x460.jpg</thumbnail>
<fanart>https://elalebrijeudl.files.wordpress.com/2018/03/tv_pit05_q5203_0038.jpg?w=1200</fanart>
</item>

<item>
<title>Cafe de Comerciantes Español Marcus Lemonis / T-4 / Cap 16</title>        
<urlsolve>http://www.dailymotion.com/video/x6allkf</urlsolve>
<thumbnail>http://www.cineymas.com.ar/wp-content/uploads/2017/04/History-El-Socio-Marcus-Lemonis-1-660x460.jpg</thumbnail>
<fanart>https://elalebrijeudl.files.wordpress.com/2018/03/tv_pit05_q5203_0038.jpg?w=1200</fanart>
</item>

<item>
<title>Paletas de helado Español Marcus Lemonis / T-4 / Cap 17</title>        
<urlsolve>http://www.dailymotion.com/video/x6b0g2o</urlsolve>
<thumbnail>http://www.cineymas.com.ar/wp-content/uploads/2017/04/History-El-Socio-Marcus-Lemonis-1-660x460.jpg</thumbnail>
<fanart>https://elalebrijeudl.files.wordpress.com/2018/03/tv_pit05_q5203_0038.jpg?w=1200</fanart>
</item>

<item>
<title>Zoe Chocolatet Marcus Lemonis / T-4 / Cap 18</title>        
<urlsolve>http://www.dailymotion.com/video/x6beiuh</urlsolve>
<thumbnail>http://www.cineymas.com.ar/wp-content/uploads/2017/04/History-El-Socio-Marcus-Lemonis-1-660x460.jpg</thumbnail>
<fanart>https://elalebrijeudl.files.wordpress.com/2018/03/tv_pit05_q5203_0038.jpg?w=1200</fanart>
</item>

<item>
<title>10 reglas para el exito Español Marcus Lemonis / T-4 / Cap 19</title>        
<urlsolve>http://www.dailymotion.com/video/x6bxww9</urlsolve>
<thumbnail>http://www.cineymas.com.ar/wp-content/uploads/2017/04/History-El-Socio-Marcus-Lemonis-1-660x460.jpg</thumbnail>
<fanart>https://elalebrijeudl.files.wordpress.com/2018/03/tv_pit05_q5203_0038.jpg?w=1200</fanart>
</item>

<item>
<title>Cap 20</title>        
<urlsolve></urlsolve>
<thumbnail></thumbnail>
<fanart></fanart>
</item>




