<?xml version="1.0" encoding="UTF-8" standalone="yes"?>

<item>
<title>Exatlhon USA - PR 2019/ Cap 1</title>        
<urlsolve>https://ok.ru/video/1812016990871</urlsolve>
<thumbnail>https://ahoramismoeditorial.files.wordpress.com/2019/02/20190203_202321-e1549245879943.jpg?quality=65&strip=all</thumbnail>
<fanart>https://laopinionla.files.wordpress.com/2018/07/exatlon-telemundo-estadosunidos-elenco.jpg?quality=80&strip=all&w=940</fanart>
</item>

<item>
<title>Exatlhon USA - PR 2019/ Cap 2</title>        
<urlsolve>https://ok.ru/video/1812017121943</urlsolve>
<thumbnail>https://laopinionla.files.wordpress.com/2018/07/exatlon-telemundo-estadosunidos-elenco.jpg?quality=80&strip=all&w=940</thumbnail>
<fanart>https://ahoramismoeditorial.files.wordpress.com/2019/02/20190203_202321-e1549245879943.jpg?quality=65&strip=all</fanart>
</item>

<item>
<title>Exatlhon USA - PR 2019/ Cap 3</title>        
<urlsolve>https://ok.ru/video/1812016728727</urlsolve>
<thumbnail>https://laopinionla.files.wordpress.com/2018/07/exatlon-telemundo-estadosunidos-elenco.jpg?quality=80&strip=all&w=940<</thumbnail>
<fanart>https://ahoramismoeditorial.files.wordpress.com/2019/02/20190203_202321-e1549245879943.jpg?quality=65&strip=all</fanart>
</item>

<item>
<title>Exatlhon USA - PR 2019/ Cap 4</title>        
<urlsolve>https://ok.ru/video/1812016925335</urlsolve>
<thumbnail>https://laopinionla.files.wordpress.com/2018/07/exatlon-telemundo-estadosunidos-elenco.jpg?quality=80&strip=all&w=940<</thumbnail>
<fanart>https://ahoramismoeditorial.files.wordpress.com/2019/02/20190203_202321-e1549245879943.jpg?quality=65&strip=all</fanart>
</item>

<item>
<title>Exatlhon USA - PR 2019/ Cap 5</title>        
<urlsolve>https://ok.ru/video/1812016597655</urlsolve>
<thumbnail>https://laopinionla.files.wordpress.com/2018/07/exatlon-telemundo-estadosunidos-elenco.jpg?quality=80&strip=all&w=940<</thumbnail>
<fanart>https://ahoramismoeditorial.files.wordpress.com/2019/02/20190203_202321-e1549245879943.jpg?quality=65&strip=all</fanart>
</item>
