<?xml version="1.0" encoding="UTF-8" standalone="yes"?>

<item>
<title>Las Muñecas De La Mafia 1 / Cap 1</title>        
<urlsolve>https://ok.ru/video/346585434690</urlsolve>
<thumbnail>https://media.metrolatam.com/2019/01/07/munecasdelamafia-6ae066721ee652c2e0f6cbc8e9b6d08b-600x400.jpg</thumbnail>
<fanart></fanart>
</item>

<item>
<title>Las Muñecas De La Mafia 1 / Cap 2</title>        
<urlsolve>https://ok.ru/video/346603194946</urlsolve>
<thumbnail>https://media.metrolatam.com/2019/01/07/munecasdelamafia-6ae066721ee652c2e0f6cbc8e9b6d08b-600x400.jpg</thumbnail>
<fanart></fanart>
</item>

<item>
<title>Las Muñecas De La Mafia 1 / Cap 3</title>        
<urlsolve>https://ok.ru/video/346827065922</urlsolve>
<thumbnail>https://media.metrolatam.com/2019/01/07/munecasdelamafia-6ae066721ee652c2e0f6cbc8e9b6d08b-600x400.jpg</thumbnail>
<fanart></fanart>
</item>

<item>
<title>Las Muñecas De La Mafia 1 / Cap 4</title>        
<urlsolve>https://ok.ru/video/346845612610</urlsolve>
<thumbnail>https://media.metrolatam.com/2019/01/07/munecasdelamafia-6ae066721ee652c2e0f6cbc8e9b6d08b-600x400.jpg</thumbnail>
<fanart></fanart>
</item>

<item>
<title>Las Muñecas De La Mafia 1 / Cap 5</title>        
<urlsolve>https://ok.ru/video/346914359874</urlsolve>
<thumbnail>https://media.metrolatam.com/2019/01/07/munecasdelamafia-6ae066721ee652c2e0f6cbc8e9b6d08b-600x400.jpg</thumbnail>
<fanart></fanart>
</item>

<item>
<title>Las Muñecas De La Mafia 1 / Cap 6</title>        
<urlsolve>https://ok.ru/video/347277625922</urlsolve>
<thumbnail>https://media.metrolatam.com/2019/01/07/munecasdelamafia-6ae066721ee652c2e0f6cbc8e9b6d08b-600x400.jpg</thumbnail>
<fanart></fanart>
</item>

<item>
<title>Las Muñecas De La Mafia 1 / Cap 7</title>        
<urlsolve>https://ok.ru/video/347296893506</urlsolve>
<thumbnail>https://media.metrolatam.com/2019/01/07/munecasdelamafia-6ae066721ee652c2e0f6cbc8e9b6d08b-600x400.jpg</thumbnail>
<fanart></fanart>
</item>

<item>
<title>Las Muñecas De La Mafia 1 / Cap 8</title>        
<urlsolve>https://ok.ru/video/348491876930</urlsolve>
<thumbnail>https://media.metrolatam.com/2019/01/07/munecasdelamafia-6ae066721ee652c2e0f6cbc8e9b6d08b-600x400.jpg</thumbnail>
<fanart></fanart>
</item>

<item>
<title>Las Muñecas De La Mafia 1 / Cap 9</title>        
<urlsolve>https://ok.ru/video/348961311298</urlsolve>
<thumbnail>https://media.metrolatam.com/2019/01/07/munecasdelamafia-6ae066721ee652c2e0f6cbc8e9b6d08b-600x400.jpg</thumbnail>
<fanart></fanart>
</item>

<item>
<title>Las Muñecas De La Mafia 1 / Cap 10</title>        
<urlsolve>https://ok.ru/video/348982086210</urlsolve>
<thumbnail>https://media.metrolatam.com/2019/01/07/munecasdelamafia-6ae066721ee652c2e0f6cbc8e9b6d08b-600x400.jpg</thumbnail>
<fanart></fanart>
</item>

<item>
<title>Las Muñecas De La Mafia 1 / Cap 11</title>        
<urlsolve>https://ok.ru/video/349382249026</urlsolve>
<thumbnail>https://media.metrolatam.com/2019/01/07/munecasdelamafia-6ae066721ee652c2e0f6cbc8e9b6d08b-600x400.jpg</thumbnail>
<fanart></fanart>
</item>

<item>
<title>Las Muñecas De La Mafia 1 / Cap 12</title>        
<urlsolve>https://ok.ru/video/349848603202</urlsolve>
<thumbnail>https://media.metrolatam.com/2019/01/07/munecasdelamafia-6ae066721ee652c2e0f6cbc8e9b6d08b-600x400.jpg</thumbnail>
<fanart></fanart>
</item>

<item>
<title>Las Muñecas De La Mafia 1 / Cap 13</title>        
<urlsolve>https://ok.ru/video/350930209346</urlsolve>
<thumbnail>https://media.metrolatam.com/2019/01/07/munecasdelamafia-6ae066721ee652c2e0f6cbc8e9b6d08b-600x400.jpg</thumbnail>
<fanart></fanart>
</item>

<item>
<title>Las Muñecas De La Mafia 1 / Cap 14</title>        
<urlsolve>https://ok.ru/video/351835195970</urlsolve>
<thumbnail>https://media.metrolatam.com/2019/01/07/munecasdelamafia-6ae066721ee652c2e0f6cbc8e9b6d08b-600x400.jpg</thumbnail>
<fanart></fanart>
</item>

<item>
<title>Las Muñecas De La Mafia 1 / Cap 15</title>        
<urlsolve>https://ok.ru/video/352365709890</urlsolve>
<thumbnail>https://media.metrolatam.com/2019/01/07/munecasdelamafia-6ae066721ee652c2e0f6cbc8e9b6d08b-600x400.jpg</thumbnail>
<fanart></fanart>
</item>

<item>
<title>Las Muñecas De La Mafia 1 / Cap 16</title>        
<urlsolve>https://ok.ru/video/353105807938</urlsolve>
<thumbnail>https://media.metrolatam.com/2019/01/07/munecasdelamafia-6ae066721ee652c2e0f6cbc8e9b6d08b-600x400.jpg</thumbnail>
<fanart></fanart>
</item>

<item>
<title>Las Muñecas De La Mafia 1 / Cap 17</title>        
<urlsolve>https://ok.ru/video/353814383170</urlsolve>
<thumbnail>https://media.metrolatam.com/2019/01/07/munecasdelamafia-6ae066721ee652c2e0f6cbc8e9b6d08b-600x400.jpg</thumbnail>
<fanart></fanart>
</item>

<item>
<title>Las Muñecas De La Mafia 1 / Cap 18</title>        
<urlsolve>https://ok.ru/video/354239056450</urlsolve>
<thumbnail>https://media.metrolatam.com/2019/01/07/munecasdelamafia-6ae066721ee652c2e0f6cbc8e9b6d08b-600x400.jpg</thumbnail>
<fanart></fanart>
</item>

<item>
<title>Las Muñecas De La Mafia 1 / Cap 19</title>        
<urlsolve>https://ok.ru/video/355777382978</urlsolve>
<thumbnail>https://media.metrolatam.com/2019/01/07/munecasdelamafia-6ae066721ee652c2e0f6cbc8e9b6d08b-600x400.jpg</thumbnail>
<fanart></fanart>
</item>

<item>
<title>Las Muñecas De La Mafia 1 / Cap 20</title>        
<urlsolve>https://ok.ru/video/356797188674</urlsolve>
<thumbnail>https://media.metrolatam.com/2019/01/07/munecasdelamafia-6ae066721ee652c2e0f6cbc8e9b6d08b-600x400.jpg</thumbnail>
<fanart></fanart>
</item>

<item>
<title>Las Muñecas De La Mafia 1 / Cap 21</title>        
<urlsolve>https://ok.ru/video/361050409538</urlsolve>
<thumbnail>https://media.metrolatam.com/2019/01/07/munecasdelamafia-6ae066721ee652c2e0f6cbc8e9b6d08b-600x400.jpg</thumbnail>
<fanart></fanart>
</item>

<item>
<title>Las Muñecas De La Mafia 1 / Cap 22</title>        
<urlsolve>https://ok.ru/video/368357345858</urlsolve>
<thumbnail>https://media.metrolatam.com/2019/01/07/munecasdelamafia-6ae066721ee652c2e0f6cbc8e9b6d08b-600x400.jpg</thumbnail>
<fanart></fanart>
</item>

<item>
<title>Las Muñecas De La Mafia 1 / Cap 23</title>        
<urlsolve>https://ok.ru/video/369768532546</urlsolve>
<thumbnail>https://media.metrolatam.com/2019/01/07/munecasdelamafia-6ae066721ee652c2e0f6cbc8e9b6d08b-600x400.jpg</thumbnail>
<fanart></fanart>
</item>

<item>
<title>Las Muñecas De La Mafia 1 / Cap 24</title>        
<urlsolve>https://ok.ru/video/378248825410</urlsolve>
<thumbnail>https://media.metrolatam.com/2019/01/07/munecasdelamafia-6ae066721ee652c2e0f6cbc8e9b6d08b-600x400.jpg</thumbnail>
<fanart></fanart>
</item>

<item>
<title>Las Muñecas De La Mafia 1 / Cap 25</title>        
<urlsolve>https://ok.ru/video/391574194754</urlsolve>
<thumbnail>https://media.metrolatam.com/2019/01/07/munecasdelamafia-6ae066721ee652c2e0f6cbc8e9b6d08b-600x400.jpg</thumbnail>
<fanart></fanart>
</item>

<item>
<title>Las Muñecas De La Mafia 1 / Cap 26</title>        
<urlsolve>https://ok.ru/video/391549880898</urlsolve>
<thumbnail>https://media.metrolatam.com/2019/01/07/munecasdelamafia-6ae066721ee652c2e0f6cbc8e9b6d08b-600x400.jpg</thumbnail>
<fanart></fanart>
</item>

<item>
<title>Las Muñecas De La Mafia 1 / Cap 27</title>        
<urlsolve>https://ok.ru/video/432865675842</urlsolve>
<thumbnail>https://media.metrolatam.com/2019/01/07/munecasdelamafia-6ae066721ee652c2e0f6cbc8e9b6d08b-600x400.jpg</thumbnail>
<fanart></fanart>
</item>

<item>
<title>Las Muñecas De La Mafia 1 / Cap 28</title>        
<urlsolve>https://ok.ru/video/432867248706</urlsolve>
<thumbnail>https://media.metrolatam.com/2019/01/07/munecasdelamafia-6ae066721ee652c2e0f6cbc8e9b6d08b-600x400.jpg</thumbnail>
<fanart></fanart>
</item>

<item>
<title>Las Muñecas De La Mafia 1 / Cap 29</title>        
<urlsolve>https://ok.ru/video/432870722114</urlsolve>
<thumbnail>https://media.metrolatam.com/2019/01/07/munecasdelamafia-6ae066721ee652c2e0f6cbc8e9b6d08b-600x400.jpg</thumbnail>
<fanart></fanart>
</item>

<item>
<title>Las Muñecas De La Mafia 1 / Cap 30</title>        
<urlsolve>https://ok.ru/video/432871901762</urlsolve>
<thumbnail>https://media.metrolatam.com/2019/01/07/munecasdelamafia-6ae066721ee652c2e0f6cbc8e9b6d08b-600x400.jpg</thumbnail>
<fanart></fanart>
</item>

<item>
<title>Las Muñecas De La Mafia 1 / Cap 31</title>        
<urlsolve>https://ok.ru/video/545209846338</urlsolve>
<thumbnail>https://media.metrolatam.com/2019/01/07/munecasdelamafia-6ae066721ee652c2e0f6cbc8e9b6d08b-600x400.jpg</thumbnail>
<fanart></fanart>
</item>

<item>
<title>Las Muñecas De La Mafia 1 / Cap 32</title>        
<urlsolve>https://ok.ru/video/545213581890</urlsolve>
<thumbnail>https://media.metrolatam.com/2019/01/07/munecasdelamafia-6ae066721ee652c2e0f6cbc8e9b6d08b-600x400.jpg</thumbnail>
<fanart></fanart>
</item>

<item>
<title>Las Muñecas De La Mafia 1 / Cap 33</title>        
<urlsolve>https://ok.ru/video/545219545666</urlsolve>
<thumbnail>https://media.metrolatam.com/2019/01/07/munecasdelamafia-6ae066721ee652c2e0f6cbc8e9b6d08b-600x400.jpg</thumbnail>
<fanart></fanart>
</item>

<item>
<title>Las Muñecas De La Mafia 1 / Cap 34</title>        
<urlsolve>https://ok.ru/video/545229244994</urlsolve>
<thumbnail>https://media.metrolatam.com/2019/01/07/munecasdelamafia-6ae066721ee652c2e0f6cbc8e9b6d08b-600x400.jpg</thumbnail>
<fanart></fanart>
</item>

<item>
<title>Las Muñecas De La Mafia 1 / Cap 35</title>        
<urlsolve>https://ok.ru/video/545235864130</urlsolve>
<thumbnail>https://media.metrolatam.com/2019/01/07/munecasdelamafia-6ae066721ee652c2e0f6cbc8e9b6d08b-600x400.jpg</thumbnail>
<fanart></fanart>
</item>

<item>
<title>Las Muñecas De La Mafia 1 / Cap 36</title>        
<urlsolve>https://ok.ru/video/545258080834</urlsolve>
<thumbnail>https://media.metrolatam.com/2019/01/07/munecasdelamafia-6ae066721ee652c2e0f6cbc8e9b6d08b-600x400.jpg</thumbnail>
<fanart></fanart>
</item>

<item>
<title>Las Muñecas De La Mafia 1 / Cap 37</title>        
<urlsolve>https://ok.ru/video/545267190338</urlsolve>
<thumbnail>https://media.metrolatam.com/2019/01/07/munecasdelamafia-6ae066721ee652c2e0f6cbc8e9b6d08b-600x400.jpg</thumbnail>
<fanart></fanart>
</item>

<item>
<title>Las Muñecas De La Mafia 1 / Cap 38</title>        
<urlsolve>https://ok.ru/video/545285605954</urlsolve>
<thumbnail>https://media.metrolatam.com/2019/01/07/munecasdelamafia-6ae066721ee652c2e0f6cbc8e9b6d08b-600x400.jpg</thumbnail>
<fanart></fanart>
</item>

<item>
<title>Las Muñecas De La Mafia 1 / Cap 39</title>        
<urlsolve>https://ok.ru/video/545294060098</urlsolve>
<thumbnail>https://media.metrolatam.com/2019/01/07/munecasdelamafia-6ae066721ee652c2e0f6cbc8e9b6d08b-600x400.jpg</thumbnail>
<fanart></fanart>
</item>

<item>
<title>Las Muñecas De La Mafia 1 / Cap 40</title>        
<urlsolve>https://ok.ru/video/555577838146</urlsolve>
<thumbnail>https://media.metrolatam.com/2019/01/07/munecasdelamafia-6ae066721ee652c2e0f6cbc8e9b6d08b-600x400.jpg</thumbnail>
<fanart></fanart>
</item>

<item>
<title>Las Muñecas De La Mafia 1 / Cap 41</title>        
<urlsolve>https://ok.ru/video/555949099586</urlsolve>
<thumbnail>https://media.metrolatam.com/2019/01/07/munecasdelamafia-6ae066721ee652c2e0f6cbc8e9b6d08b-600x400.jpg</thumbnail>
<fanart></fanart>
</item>

<item>
<title>Las Muñecas De La Mafia 1 / Cap 42</title>        
<urlsolve>https://ok.ru/video/555951131202</urlsolve>
<thumbnail>https://media.metrolatam.com/2019/01/07/munecasdelamafia-6ae066721ee652c2e0f6cbc8e9b6d08b-600x400.jpg</thumbnail>
<fanart></fanart>
</item>

<item>
<title>Las Muñecas De La Mafia 1 / Cap 43</title>        
<urlsolve>https://ok.ru/video/555953818178</urlsolve>
<thumbnail>https://media.metrolatam.com/2019/01/07/munecasdelamafia-6ae066721ee652c2e0f6cbc8e9b6d08b-600x400.jpg</thumbnail>
<fanart></fanart>
</item>

<item>
<title>Las Muñecas De La Mafia 1 / Cap 44</title>        
<urlsolve>https://ok.ru/video/555956898370</urlsolve>
<thumbnail>https://media.metrolatam.com/2019/01/07/munecasdelamafia-6ae066721ee652c2e0f6cbc8e9b6d08b-600x400.jpg</thumbnail>
<fanart></fanart>
</item>

<item>
<title>Las Muñecas De La Mafia 1 / Cap 45</title>        
<urlsolve>https://ok.ru/video/555960764994</urlsolve>
<thumbnail>https://media.metrolatam.com/2019/01/07/munecasdelamafia-6ae066721ee652c2e0f6cbc8e9b6d08b-600x400.jpg</thumbnail>
<fanart></fanart>
</item>

<item>
<title>Las Muñecas De La Mafia 1 / Cap 46</title>        
<urlsolve>https://ok.ru/video/555965418050</urlsolve>
<thumbnail>https://media.metrolatam.com/2019/01/07/munecasdelamafia-6ae066721ee652c2e0f6cbc8e9b6d08b-600x400.jpg</thumbnail>
<fanart></fanart>
</item>

<item>
<title>Las Muñecas De La Mafia 1 / Cap 47</title>        
<urlsolve>https://ok.ru/video/555967777346</urlsolve>
<thumbnail>https://media.metrolatam.com/2019/01/07/munecasdelamafia-6ae066721ee652c2e0f6cbc8e9b6d08b-600x400.jpg</thumbnail>
<fanart></fanart>
</item>

<item>
<title>Las Muñecas De La Mafia 1 / Cap 48</title>        
<urlsolve>https://ok.ru/video/555970333250</urlsolve>
<thumbnail>https://media.metrolatam.com/2019/01/07/munecasdelamafia-6ae066721ee652c2e0f6cbc8e9b6d08b-600x400.jpg</thumbnail>
<fanart></fanart>
</item>

<item>
<title>Las Muñecas De La Mafia 1 / Cap 49</title>        
<urlsolve>https://ok.ru/video/555974658626</urlsolve>
<thumbnail>https://media.metrolatam.com/2019/01/07/munecasdelamafia-6ae066721ee652c2e0f6cbc8e9b6d08b-600x400.jpg</thumbnail>
<fanart></fanart>
</item>

<item>
<title>Las Muñecas De La Mafia 1 / Cap 50</title>        
<urlsolve>https://ok.ru/video/673060096578</urlsolve>
<thumbnail>https://media.metrolatam.com/2019/01/07/munecasdelamafia-6ae066721ee652c2e0f6cbc8e9b6d08b-600x400.jpg</thumbnail>
<fanart></fanart>
</item>

<item>
<title>Las Muñecas De La Mafia 1 / Cap 51</title>        
<urlsolve>https://ok.ru/video/673067043394</urlsolve>
<thumbnail>https://media.metrolatam.com/2019/01/07/munecasdelamafia-6ae066721ee652c2e0f6cbc8e9b6d08b-600x400.jpg</thumbnail>
<fanart></fanart>
</item>

<item>
<title>Las Muñecas De La Mafia 1 / Cap 52</title>        
<urlsolve>https://ok.ru/video/673084541506</urlsolve>
<thumbnail>https://media.metrolatam.com/2019/01/07/munecasdelamafia-6ae066721ee652c2e0f6cbc8e9b6d08b-600x400.jpg</thumbnail>
<fanart></fanart>
</item>

<item>
<title>Las Muñecas De La Mafia 1 / Cap </title>        
<urlsolve></urlsolve>
<thumbnail>https://media.metrolatam.com/2019/01/07/munecasdelamafia-6ae066721ee652c2e0f6cbc8e9b6d08b-600x400.jpg</thumbnail>
<fanart></fanart>
</item>

<item>
<title>Las Muñecas De La Mafia 1 / Cap </title>        
<urlsolve></urlsolve>
<thumbnail>https://media.metrolatam.com/2019/01/07/munecasdelamafia-6ae066721ee652c2e0f6cbc8e9b6d08b-600x400.jpg</thumbnail>
<fanart></fanart>
</item>

<item>
<title>Las Muñecas De La Mafia 1 / Cap </title>        
<urlsolve></urlsolve>
<thumbnail>https://media.metrolatam.com/2019/01/07/munecasdelamafia-6ae066721ee652c2e0f6cbc8e9b6d08b-600x400.jpg</thumbnail>
<fanart></fanart>
</item>
