<?xml version="1.0" encoding="UTF-8" standalone="yes"?>

<item>
<title>La Viuda Negra T1 / Cap 1</title>        
<urlsolve>https://ok.ru/video/40862091934</urlsolve>
<thumbnail>https://i2.wp.com/otlsm.com/wp-content/uploads/2017/01/img_0152.jpg?resize=193%2C283</thumbnail>
<fanart></fanart>
</item>

<item>
<title>La Viuda Negra T1 / Cap 2</title>        
<urlsolve>https://ok.ru/video/40901413534</urlsolve>
<thumbnail>https://i2.wp.com/otlsm.com/wp-content/uploads/2017/01/img_0152.jpg?resize=193%2C283</thumbnail>
<fanart></fanart>
</item>

<item>
<title>La Viuda Negra T1 / Cap 3</title>        
<urlsolve>https://ok.ru/video/40934902430</urlsolve>
<thumbnail>https://i2.wp.com/otlsm.com/wp-content/uploads/2017/01/img_0152.jpg?resize=193%2C283</thumbnail>
<fanart></fanart>
</item>

<item>
<title>La Viuda Negra T1 / Cap 4</title>        
<urlsolve>https://ok.ru/video/40921074334</urlsolve>
<thumbnail>https://i2.wp.com/otlsm.com/wp-content/uploads/2017/01/img_0152.jpg?resize=193%2C283</thumbnail>
<fanart></fanart>
</item>

<item>
<title>La Viuda Negra T1 / Cap 5</title>        
<urlsolve>https://ok.ru/video/40894925470</urlsolve>
<thumbnail>https://i2.wp.com/otlsm.com/wp-content/uploads/2017/01/img_0152.jpg?resize=193%2C283</thumbnail>
<fanart></fanart>
</item>

<item>
<title>La Viuda Negra T1 / Cap 6</title>        
<urlsolve>https://ok.ru/video/40875133598</urlsolve>
<thumbnail>https://i2.wp.com/otlsm.com/wp-content/uploads/2017/01/img_0152.jpg?resize=193%2C283</thumbnail>
<fanart></fanart>
</item>

<item>
<title>La Viuda Negra T1 / Cap 7</title>        
<urlsolve>https://ok.ru/video/40862157470</urlsolve>
<thumbnail>https://i2.wp.com/otlsm.com/wp-content/uploads/2017/01/img_0152.jpg?resize=193%2C283</thumbnail>
<fanart></fanart>
</item>

<item>
<title>La Viuda Negra T1 / Cap 8</title>        
<urlsolve>https://ok.ru/video/40869038750</urlsolve>
<thumbnail>https://i2.wp.com/otlsm.com/wp-content/uploads/2017/01/img_0152.jpg?resize=193%2C283</thumbnail>
<fanart></fanart>
</item>

<item>
<title>La Viuda Negra T1 / Cap 9</title>        
<urlsolve>https://ok.ru/video/40829389470</urlsolve>
<thumbnail>https://i2.wp.com/otlsm.com/wp-content/uploads/2017/01/img_0152.jpg?resize=193%2C283</thumbnail>
<fanart></fanart>
</item>

<item>
<title>La Viuda Negra T1 / Cap 10</title>        
<urlsolve>https://ok.ru/video/40855866014</urlsolve>
<thumbnail>https://i2.wp.com/otlsm.com/wp-content/uploads/2017/01/img_0152.jpg?resize=193%2C283</thumbnail>
<fanart></fanart>
</item>

<item>
<title>La Viuda Negra T1 / Cap 11</title>        
<urlsolve>https://ok.ru/video/40896039582</urlsolve>
<thumbnail>https://i2.wp.com/otlsm.com/wp-content/uploads/2017/01/img_0152.jpg?resize=193%2C283</thumbnail>
<fanart></fanart>
</item>

<item>
<title>La Viuda Negra T1 / Cap 12</title>        
<urlsolve>https://ok.ru/video/40915176094</urlsolve>
<thumbnail>https://i2.wp.com/otlsm.com/wp-content/uploads/2017/01/img_0152.jpg?resize=193%2C283</thumbnail>
<fanart></fanart>
</item>

<item>
<title>La Viuda Negra T1 / Cap 13</title>        
<urlsolve>https://ok.ru/video/40836729502</urlsolve>
<thumbnail>https://i2.wp.com/otlsm.com/wp-content/uploads/2017/01/img_0152.jpg?resize=193%2C283</thumbnail>
<fanart></fanart>
</item>

<item>
<title>La Viuda Negra T1 / Cap 14</title>        
<urlsolve>https://ok.ru/video/40876182174</urlsolve>
<thumbnail>https://i2.wp.com/otlsm.com/wp-content/uploads/2017/01/img_0152.jpg?resize=193%2C283</thumbnail>
<fanart></fanart>
</item>

<item>
<title>La Viuda Negra T1 / Cap 15</title>        
<urlsolve>https://ok.ru/video/40823360158</urlsolve>
<thumbnail>https://i2.wp.com/otlsm.com/wp-content/uploads/2017/01/img_0152.jpg?resize=193%2C283</thumbnail>
<fanart></fanart>
</item>

<item>
<title>La Viuda Negra T1 / Cap 16</title>        
<urlsolve>https://ok.ru/video/40836795038</urlsolve>
<thumbnail>https://i2.wp.com/otlsm.com/wp-content/uploads/2017/01/img_0152.jpg?resize=193%2C283</thumbnail>
<fanart></fanart>
</item>

<item>
<title>La Viuda Negra T1 / Cap 17</title>        
<urlsolve>https://ok.ru/video/40830438046</urlsolve>
<thumbnail>https://i2.wp.com/otlsm.com/wp-content/uploads/2017/01/img_0152.jpg?resize=193%2C283</thumbnail>
<fanart></fanart>
</item>

<item>
<title>La Viuda Negra T1 / Cap 18</title>        
<urlsolve>https://ok.ru/video/40882735774</urlsolve>
<thumbnail>https://i2.wp.com/otlsm.com/wp-content/uploads/2017/01/img_0152.jpg?resize=193%2C283</thumbnail>
<fanart></fanart>
</item>

<item>
<title>La Viuda Negra T1 / Cap 19</title>        
<urlsolve>https://ok.ru/video/40823425694</urlsolve>
<thumbnail>https://i2.wp.com/otlsm.com/wp-content/uploads/2017/01/img_0152.jpg?resize=193%2C283</thumbnail>
<fanart></fanart>
</item>

<item>
<title>La Viuda Negra T1 / Cap 20</title>        
<urlsolve>https://ok.ru/video/40902134430</urlsolve>
<thumbnail>https://i2.wp.com/otlsm.com/wp-content/uploads/2017/01/img_0152.jpg?resize=193%2C283</thumbnail>
<fanart></fanart>
</item>

<item>
<title>La Viuda Negra T1 / Cap 21</title>        
<urlsolve>https://ok.ru/video/40908688030</urlsolve>
<thumbnail>https://i2.wp.com/otlsm.com/wp-content/uploads/2017/01/img_0152.jpg?resize=193%2C283</thumbnail>
<fanart></fanart>
</item>

<item>
<title>La Viuda Negra T1 / Cap 22</title>        
<urlsolve>https://ok.ru/video/40876247710</urlsolve>
<thumbnail>https://i2.wp.com/otlsm.com/wp-content/uploads/2017/01/img_0152.jpg?resize=193%2C283</thumbnail>
<fanart></fanart>
</item>

<item>
<title>La Viuda Negra T1 / Cap 23</title>        
<urlsolve>https://ok.ru/video/40902199966</urlsolve>
<thumbnail>https://i2.wp.com/otlsm.com/wp-content/uploads/2017/01/img_0152.jpg?resize=193%2C283</thumbnail>
<fanart></fanart>
</item>

<item>
<title>La Viuda Negra T1 / Cap 24</title>        
<urlsolve>https://ok.ru/video/40889551518</urlsolve>
<thumbnail>https://i2.wp.com/otlsm.com/wp-content/uploads/2017/01/img_0152.jpg?resize=193%2C283</thumbnail>
<fanart></fanart>
</item>

<item>
<title>La Viuda Negra T1 / Cap 25</title>        
<urlsolve>https://ok.ru/video/40902265502</urlsolve>
<thumbnail>https://i2.wp.com/otlsm.com/wp-content/uploads/2017/01/img_0152.jpg?resize=193%2C283</thumbnail>
<fanart></fanart>
</item>

<item>
<title>La Viuda Negra T1 / Cap 26</title>        
<urlsolve>https://ok.ru/video/40908753566</urlsolve>
<thumbnail>https://i2.wp.com/otlsm.com/wp-content/uploads/2017/01/img_0152.jpg?resize=193%2C283</thumbnail>
<fanart></fanart>
</item>

<item>
<title>La Viuda Negra T1 / Cap 27</title>        
<urlsolve>https://ok.ru/video/40876313246</urlsolve>
<thumbnail>https://i2.wp.com/otlsm.com/wp-content/uploads/2017/01/img_0152.jpg?resize=193%2C283</thumbnail>
<fanart></fanart>
</item>

<item>
<title>La Viuda Negra T1 / Cap 28</title>        
<urlsolve>https://ok.ru/video/40863009438</urlsolve>
<thumbnail>https://i2.wp.com/otlsm.com/wp-content/uploads/2017/01/img_0152.jpg?resize=193%2C283</thumbnail>
<fanart></fanart>
</item>

<item>
<title>La Viuda Negra T1 / Cap 29</title>        
<urlsolve>https://ok.ru/video/40869890718</urlsolve>
<thumbnail>https://i2.wp.com/otlsm.com/wp-content/uploads/2017/01/img_0152.jpg?resize=193%2C283</thumbnail>
<fanart></fanart>
</item>

<item>
<title>La Viuda Negra T1 / Cap 30</title>        
<urlsolve>https://ok.ru/video/40889617054</urlsolve>
<thumbnail>https://i2.wp.com/otlsm.com/wp-content/uploads/2017/01/img_0152.jpg?resize=193%2C283</thumbnail>
<fanart></fanart>
</item>

<item>
<title>La Viuda Negra T1 / Cap 31</title>        
<urlsolve>https://ok.ru/video/40929004190</urlsolve>
<thumbnail>https://i2.wp.com/otlsm.com/wp-content/uploads/2017/01/img_0152.jpg?resize=193%2C283</thumbnail>
<fanart></fanart>
</item>

<item>
<title>La Viuda Negra T1 / Cap 32</title>        
<urlsolve>https://ok.ru/video/40922253982</urlsolve>
<thumbnail>https://i2.wp.com/otlsm.com/wp-content/uploads/2017/01/img_0152.jpg?resize=193%2C283</thumbnail>
<fanart></fanart>
</item>

<item>
<title>La Viuda Negra T1 / Cap 33</title>        
<urlsolve>https://ok.ru/video/40830503582</urlsolve>
<thumbnail>https://i2.wp.com/otlsm.com/wp-content/uploads/2017/01/img_0152.jpg?resize=193%2C283</thumbnail>
<fanart></fanart>
</item>

<item>
<title>La Viuda Negra T1 / Cap 34</title>        
<urlsolve>https://ok.ru/video/40850360990</urlsolve>
<thumbnail>https://i2.wp.com/otlsm.com/wp-content/uploads/2017/01/img_0152.jpg?resize=193%2C283</thumbnail>
<fanart></fanart>
</item>

<item>
<title>La Viuda Negra T1 / Cap 35</title>        
<urlsolve>https://ok.ru/video/40882801310</urlsolve>
<thumbnail>https://i2.wp.com/otlsm.com/wp-content/uploads/2017/01/img_0152.jpg?resize=193%2C283</thumbnail>
<fanart></fanart>
</item>

<item>
<title>La Viuda Negra T1 / Cap 36</title>        
<urlsolve>https://ok.ru/video/40842758814</urlsolve>
<thumbnail>https://i2.wp.com/otlsm.com/wp-content/uploads/2017/01/img_0152.jpg?resize=193%2C283</thumbnail>
<fanart></fanart>
</item>

<item>
<title>La Viuda Negra T1 / Cap 37</title>        
<urlsolve>https://ok.ru/video/40823491230</urlsolve>
<thumbnail>https://i2.wp.com/otlsm.com/wp-content/uploads/2017/01/img_0152.jpg?resize=193%2C283</thumbnail>
<fanart></fanart>
</item>

<item>
<title>La Viuda Negra T1 / Cap 38</title>        
<urlsolve>https://ok.ru/video/40902331038</urlsolve>
<thumbnail>https://i2.wp.com/otlsm.com/wp-content/uploads/2017/01/img_0152.jpg?resize=193%2C283</thumbnail>
<fanart></fanart>
</item>

<item>
<title>La Viuda Negra T1 / Cap 39</title>        
<urlsolve>https://ok.ru/video/40929069726</urlsolve>
<thumbnail>https://i2.wp.com/otlsm.com/wp-content/uploads/2017/01/img_0152.jpg?resize=193%2C283</thumbnail>
<fanart></fanart>
</item>

<item>
<title>La Viuda Negra T1 / Cap 40</title>        
<urlsolve>https://ok.ru/video/40889682590</urlsolve>
<thumbnail>https://i2.wp.com/otlsm.com/wp-content/uploads/2017/01/img_0152.jpg?resize=193%2C283</thumbnail>
<fanart></fanart>
</item>

<item>
<title>La Viuda Negra T1 / Cap 41</title>        
<urlsolve>https://ok.ru/video/40871398046</urlsolve>
<thumbnail>https://i2.wp.com/otlsm.com/wp-content/uploads/2017/01/img_0152.jpg?resize=193%2C283</thumbnail>
<fanart></fanart>
</item>

<item>
<title>La Viuda Negra T1 / Cap 42</title>        
<urlsolve>https://ok.ru/video/40877886110</urlsolve>
<thumbnail>https://i2.wp.com/otlsm.com/wp-content/uploads/2017/01/img_0152.jpg?resize=193%2C283</thumbnail>
<fanart></fanart>
</item>

<item>
<title>La Viuda Negra T1 / Cap 43</title>        
<urlsolve>https://ok.ru/video/40852523678</urlsolve>
<thumbnail>https://i2.wp.com/otlsm.com/wp-content/uploads/2017/01/img_0152.jpg?resize=193%2C283</thumbnail>
<fanart></fanart>
</item>

<item>
<title>La Viuda Negra T1 / Cap 44</title>        
<urlsolve>https://ok.ru/video/40930773662</urlsolve>
<thumbnail>https://i2.wp.com/otlsm.com/wp-content/uploads/2017/01/img_0152.jpg?resize=193%2C283</thumbnail>
<fanart></fanart>
</item>

<item>
<title>La Viuda Negra T1 / Cap 45</title>        
<urlsolve>https://ok.ru/video/40936802974</urlsolve>
<thumbnail>https://i2.wp.com/otlsm.com/wp-content/uploads/2017/01/img_0152.jpg?resize=193%2C283</thumbnail>
<fanart></fanart>
</item>

<item>
<title>La Viuda Negra T1 / Cap 46</title>        
<urlsolve>https://ok.ru/video/40917011102</urlsolve>
<thumbnail>https://i2.wp.com/otlsm.com/wp-content/uploads/2017/01/img_0152.jpg?resize=193%2C283</thumbnail>
<fanart></fanart>
</item>

<item>
<title>La Viuda Negra T1 / Cap 47</title>        
<urlsolve>https://ok.ru/video/40832862878</urlsolve>
<thumbnail>https://i2.wp.com/otlsm.com/wp-content/uploads/2017/01/img_0152.jpg?resize=193%2C283</thumbnail>
<fanart></fanart>
</item>

<item>
<title>La Viuda Negra T1 / Cap 48</title>        
<urlsolve>https://ok.ru/video/40844200606</urlsolve>
<thumbnail>https://i2.wp.com/otlsm.com/wp-content/uploads/2017/01/img_0152.jpg?resize=193%2C283</thumbnail>
<fanart></fanart>
</item>

<item>
<title>La Viuda Negra T1 / Cap 49</title>        
<urlsolve>https://ok.ru/video/40890862238</urlsolve>
<thumbnail>https://i2.wp.com/otlsm.com/wp-content/uploads/2017/01/img_0152.jpg?resize=193%2C283</thumbnail>
<fanart></fanart>
</item>

<item>
<title>La Viuda Negra T1 / Cap 50</title>        
<urlsolve>https://ok.ru/video/40973830814</urlsolve>
<thumbnail>https://i2.wp.com/otlsm.com/wp-content/uploads/2017/01/img_0152.jpg?resize=193%2C283</thumbnail>
<fanart></fanart>
</item>

<item>
<title>La Viuda Negra T1 / Cap 51</title>        
<urlsolve>https://ok.ru/video/41000438430</urlsolve>
<thumbnail>https://i2.wp.com/otlsm.com/wp-content/uploads/2017/01/img_0152.jpg?resize=193%2C283</thumbnail>
<fanart></fanart>
</item>

<item>
<title>La Viuda Negra T1 / Cap 52</title>        
<urlsolve>https://ok.ru/video/40980318878</urlsolve>
<thumbnail>https://i2.wp.com/otlsm.com/wp-content/uploads/2017/01/img_0152.jpg?resize=193%2C283</thumbnail>
<fanart></fanart>
</item>

<item>
<title>La Viuda Negra T1 / Cap 53</title>        
<urlsolve>https://ok.ru/video/41032419998</urlsolve>
<thumbnail>https://i2.wp.com/otlsm.com/wp-content/uploads/2017/01/img_0152.jpg?resize=193%2C283</thumbnail>
<fanart></fanart>
</item>

<item>
<title>La Viuda Negra T1 / Cap 54</title>        
<urlsolve>https://ok.ru/video/40917142174</urlsolve>
<thumbnail>https://i2.wp.com/otlsm.com/wp-content/uploads/2017/01/img_0152.jpg?resize=193%2C283</thumbnail>
<fanart></fanart>
</item>

<item>
<title>La Viuda Negra T1 / Cap 55</title>        
<urlsolve>https://ok.ru/video/40838105758</urlsolve>
<thumbnail>https://i2.wp.com/otlsm.com/wp-content/uploads/2017/01/img_0152.jpg?resize=193%2C283</thumbnail>
<fanart></fanart>
</item>

<item>
<title>La Viuda Negra T1 / Cap 56</title>        
<urlsolve>https://ok.ru/video/40878017182</urlsolve>
<thumbnail>https://i2.wp.com/otlsm.com/wp-content/uploads/2017/01/img_0152.jpg?resize=193%2C283</thumbnail>
<fanart></fanart>
</item>

<item>
<title>La Viuda Negra T1 / Cap 57</title>        
<urlsolve>https://ok.ru/video/40910129822</urlsolve>
<thumbnail>https://i2.wp.com/otlsm.com/wp-content/uploads/2017/01/img_0152.jpg?resize=193%2C283</thumbnail>
<fanart></fanart>
</item>

<item>
<title>La Viuda Negra T1 / Cap 58</title>        
<urlsolve>https://ok.ru/video/40884701854</urlsolve>
<thumbnail>https://i2.wp.com/otlsm.com/wp-content/uploads/2017/01/img_0152.jpg?resize=193%2C283</thumbnail>
<fanart></fanart>
</item>

<item>
<title>La Viuda Negra T1 / Cap 59</title>        
<urlsolve>https://ok.ru/video/40878082718</urlsolve>
<thumbnail>https://i2.wp.com/otlsm.com/wp-content/uploads/2017/01/img_0152.jpg?resize=193%2C283</thumbnail>
<fanart></fanart>
</item>

<item>
<title>La Viuda Negra T1 / Cap 60</title>        
<urlsolve>https://ok.ru/video/40878148254</urlsolve>
<thumbnail>https://i2.wp.com/otlsm.com/wp-content/uploads/2017/01/img_0152.jpg?resize=193%2C283</thumbnail>
<fanart></fanart>
</item>

<item>
<title>La Viuda Negra T1 / Cap 61</title>        
<urlsolve>https://ok.ru/video/40897940126</urlsolve>
<thumbnail>https://i2.wp.com/otlsm.com/wp-content/uploads/2017/01/img_0152.jpg?resize=193%2C283</thumbnail>
<fanart></fanart>
</item>

<item>
<title>La Viuda Negra T1 / Cap 62</title>        
<urlsolve>https://ok.ru/video/40930839198</urlsolve>
<thumbnail>https://i2.wp.com/otlsm.com/wp-content/uploads/2017/01/img_0152.jpg?resize=193%2C283</thumbnail>
<fanart></fanart>
</item>

<item>
<title>La Viuda Negra T1 / Cap 63</title>        
<urlsolve>https://ok.ru/video/40864385694</urlsolve>
<thumbnail>https://i2.wp.com/otlsm.com/wp-content/uploads/2017/01/img_0152.jpg?resize=193%2C283</thumbnail>
<fanart></fanart>
</item>

<item>
<title>La Viuda Negra T1 / Cap 64</title>        
<urlsolve>https://ok.ru/video/40838171294</urlsolve>
<thumbnail>https://i2.wp.com/otlsm.com/wp-content/uploads/2017/01/img_0152.jpg?resize=193%2C283</thumbnail>
<fanart></fanart>
</item>

<item>
<title>La Viuda Negra T1 / Cap 65</title>        
<urlsolve>https://ok.ru/video/40838236830</urlsolve>
<thumbnail>https://i2.wp.com/otlsm.com/wp-content/uploads/2017/01/img_0152.jpg?resize=193%2C283</thumbnail>
<fanart></fanart>
</item>

<item>
<title>La Viuda Negra T1 / Cap 66</title>        
<urlsolve>https://ok.ru/video/40930904734</urlsolve>
<thumbnail>https://i2.wp.com/otlsm.com/wp-content/uploads/2017/01/img_0152.jpg?resize=193%2C283</thumbnail>
<fanart></fanart>
</item>

<item>
<title>La Viuda Negra T1 / Cap 67</title>        
<urlsolve>https://ok.ru/video/40910195358</urlsolve>
<thumbnail>https://i2.wp.com/otlsm.com/wp-content/uploads/2017/01/img_0152.jpg?resize=193%2C283</thumbnail>
<fanart></fanart>
</item>

<item>
<title>La Viuda Negra T1 / Cap 68</title>        
<urlsolve>https://ok.ru/video/40878213790</urlsolve>
<thumbnail>https://i2.wp.com/otlsm.com/wp-content/uploads/2017/01/img_0152.jpg?resize=193%2C283</thumbnail>
<fanart></fanart>
</item>

<item>
<title>La Viuda Negra T1 / Cap 69</title>        
<urlsolve>https://ok.ru/video/40878279326</urlsolve>
<thumbnail>https://i2.wp.com/otlsm.com/wp-content/uploads/2017/01/img_0152.jpg?resize=193%2C283</thumbnail>
<fanart></fanart>
</item>

<item>
<title>La Viuda Negra T1 / Cap 70</title>        
<urlsolve>https://ok.ru/video/40898005662</urlsolve>
<thumbnail>https://i2.wp.com/otlsm.com/wp-content/uploads/2017/01/img_0152.jpg?resize=193%2C283</thumbnail>
<fanart></fanart>
</item>

<item>
<title>La Viuda Negra T1 / Cap 71</title>        
<urlsolve>https://ok.ru/video/40858094238</urlsolve>
<thumbnail>https://i2.wp.com/otlsm.com/wp-content/uploads/2017/01/img_0152.jpg?resize=193%2C283</thumbnail>
<fanart></fanart>
</item>

<item>
<title>La Viuda Negra T1 / Cap 72</title>        
<urlsolve>https://ok.ru/video/40930970270</urlsolve>
<thumbnail>https://i2.wp.com/otlsm.com/wp-content/uploads/2017/01/img_0152.jpg?resize=193%2C283</thumbnail>
<fanart></fanart>
</item>

<item>
<title>La Viuda Negra T1 / Cap 73</title>        
<urlsolve>https://ok.ru/video/40864451230</urlsolve>
<thumbnail>https://i2.wp.com/otlsm.com/wp-content/uploads/2017/01/img_0152.jpg?resize=193%2C283</thumbnail>
<fanart></fanart>
</item>

<item>
<title>La Viuda Negra T1 / Cap 74</title>        
<urlsolve>https://ok.ru/video/40910260894</urlsolve>
<thumbnail>https://i2.wp.com/otlsm.com/wp-content/uploads/2017/01/img_0152.jpg?resize=193%2C283</thumbnail>
<fanart></fanart>
</item>

<item>
<title>La Viuda Negra T1 / Cap 75</title>        
<urlsolve>https://ok.ru/video/40936868510</urlsolve>
<thumbnail>https://i2.wp.com/otlsm.com/wp-content/uploads/2017/01/img_0152.jpg?resize=193%2C283</thumbnail>
<fanart></fanart>
</item>

<item>
<title>La Viuda Negra T1 / Cap 76</title>        
<urlsolve></urlsolve>
<thumbnail>https://i2.wp.com/otlsm.com/wp-content/uploads/2017/01/img_0152.jpg?resize=193%2C283</thumbnail>
<fanart></fanart>
</item>

<item>
<title>La Viuda Negra T1 / Cap 77</title>        
<urlsolve></urlsolve>
<thumbnail>https://i2.wp.com/otlsm.com/wp-content/uploads/2017/01/img_0152.jpg?resize=193%2C283</thumbnail>
<fanart></fanart>
</item>

<item>
<title>La Viuda Negra T1 / Cap 78</title>        
<urlsolve></urlsolve>
<thumbnail>https://i2.wp.com/otlsm.com/wp-content/uploads/2017/01/img_0152.jpg?resize=193%2C283</thumbnail>
<fanart></fanart>
</item>

<item>
<title>La Viuda Negra T1 / Cap 79</title>        
<urlsolve></urlsolve>
<thumbnail>https://i2.wp.com/otlsm.com/wp-content/uploads/2017/01/img_0152.jpg?resize=193%2C283</thumbnail>
<fanart></fanart>
</item>

<item>
<title>La Viuda Negra T1 / Cap 80</title>        
<urlsolve></urlsolve>
<thumbnail>https://i2.wp.com/otlsm.com/wp-content/uploads/2017/01/img_0152.jpg?resize=193%2C283</thumbnail>
<fanart></fanart>
</item>
